AUTHORS
LICENSE
MANIFEST.in
README.md
setup.py
multi_health/__init__.py
multi_health/models.py
multi_health/urls.py
multi_health/views.py
multi_health/management/__init__.py
multi_health/management/commands/__init__.py
multi_health/management/commands/multisite_healthcheck.py
multi_health/templates/multi_health/results_table.html
multisite_healthcheck.egg-info/PKG-INFO
multisite_healthcheck.egg-info/SOURCES.txt
multisite_healthcheck.egg-info/dependency_links.txt
multisite_healthcheck.egg-info/requires.txt
multisite_healthcheck.egg-info/top_level.txt