Metadata-Version: 1.1
Name: multisite-healthcheck
Version: 0.2.1
Summary: Django app to check the status of sites in a multi-website django environment.
Home-page: https://github.com/DanielKirov/multisite-healthcheck
Author: Daniel Kirov
Author-email: daniel.kirov@pancentric.com
License: BSD License
Platform: UNKNOWN
Classifier: Environment :: Web Environment
Classifier: Framework :: Django
Classifier: Intended Audience :: Developers
Classifier: License :: OSI Approved :: BSD License
Classifier: Operating System :: OS Independent
Classifier: Programming Language :: Python
Classifier: Programming Language :: Python :: 2
Classifier: Programming Language :: Python :: 2.7
Classifier: Topic :: Internet :: WWW/HTTP
Classifier: Topic :: Internet :: WWW/HTTP :: Dynamic Content
